[{"Id":38,"Group":1,"Item":2714,"Amount":1,"Enabled":true,"Type":"Leatherworker","IsPrimary":true},{"Id":39,"Group":1,"Item":3052,"Amount":1,"Enabled":true,"Type":"Weaver","IsPrimary":true},{"Id":40,"Group":1,"Item":3562,"Amount":1,"Enabled":true,"Type":"Leatherworker","IsPrimary":true},{"Id":41,"Group":1,"Item":3982,"Amount":1,"Enabled":true,"Type":"Leatherworker","IsPrimary":true},{"Id":42,"Group":1,"Item":3336,"Amount":1,"Enabled":true,"Type":"Weaver","IsPrimary":true},{"Id":43,"Group":1,"Item":3795,"Amount":1,"Enabled":true,"Type":"Leatherworker","IsPrimary":true},{"Id":44,"Group":1,"Item":4204,"Amount":1,"Enabled":true,"Type":"Goldsmith","IsPrimary":true},{"Id":45,"Group":1,"Item":4313,"Amount":1,"Enabled":true,"Type":"Goldsmith","IsPrimary":true},{"Id":46,"Group":1,"Item":4095,"Amount":1,"Enabled":true,"Type":"Goldsmith","IsPrimary":true},{"Id":47,"Group":1,"Item":4431,"Amount":2,"Enabled":true,"Type":"Goldsmith","IsPrimary":true},{"Id":96,"Group":1,"Item":2471,"Amount":1,"Enabled":true,"Type":"Armorer","IsPrimary":true},{"Id":97,"Group":1,"Item":2484,"Amount":1,"Enabled":true,"Type":"Blacksmith","IsPrimary":true}]